uv_sort/__init__.py
uv_sort/_version.py
uv_sort/_version.pyi
uv_sort/cli.py
uv_sort/main.py
uv_sort-0.7.0.dist-info/METADATA
uv_sort-0.7.0.dist-info/WHEEL
uv_sort-0.7.0.dist-info/entry_points.txt
uv_sort-0.7.0.dist-info/licenses/LICENSE
uv_sort-0.7.0.dist-info/RECORD
