Metadata-Version: 2.4
Name: uv-sort
Version: 0.7.0
Summary: Sort uv's dependencies alphabetically
Project-URL: Repository, https://github.com/ninoseki/uv-sort
License: MIT License
License-File: LICENSE
Keywords: uv
Classifier: License :: OSI Approved :: MIT License
Classifier: Programming Language :: Python
Classifier: Programming Language :: Python :: 3.10
Classifier: Programming Language :: Python :: 3.11
Classifier: Programming Language :: Python :: 3.12
Classifier: Programming Language :: Python :: 3.13
Classifier: Programming Language :: Python :: 3.14
Requires-Python: >=3.10
Requires-Dist: packaging>=24.1
Requires-Dist: tomlkit~=0.13
Requires-Dist: typer>=0.15
